vnova/__init__.py
vnova/vc6_cu12/PRIVACY.md
vnova/vc6_cu12/PyVc6IL.so
vnova/vc6_cu12/README.md
vnova/vc6_cu12/Vc6Utils.py
vnova/vc6_cu12/_PyVc6ILUtils.so
vnova/vc6_cu12/__init__.py
vnova/vc6_cu12/codec.py
vnova/vc6_cu12/utils.py
vnova/vc6_cu12/vc6il.py
vc6_cu12-7.30.0.dist-info/METADATA
vc6_cu12-7.30.0.dist-info/WHEEL
vc6_cu12-7.30.0.dist-info/top_level.txt
vc6_cu12-7.30.0.dist-info/RECORD
vc6_cu12-7.30.0.dist-info/licenses/LICENSE.txt
