Metadata-Version: 2.4
Name: vc6_cu12
Version: 7.30.0
Summary: V-Nova VC-6 codec Python bindings (cu12 backend).
Author-email: V-Nova <info@v-nova.com>
License: Proprietary - see LICENSE.txt
Project-URL: Homepage, https://www.v-nova.com/
Classifier: Development Status :: 4 - Beta
Classifier: Intended Audience :: Developers
Classifier: License :: Other/Proprietary License
Classifier: Operating System :: POSIX :: Linux
Classifier: Operating System :: Microsoft :: Windows
Classifier: Operating System :: MacOS :: MacOS X
Classifier: Programming Language :: Python :: 3
Classifier: Programming Language :: Python :: 3.8
Classifier: Programming Language :: Python :: 3.9
Classifier: Programming Language :: Python :: 3.10
Classifier: Programming Language :: Python :: 3.11
Classifier: Programming Language :: Python :: 3.12
Classifier: Programming Language :: C++
Classifier: Topic :: Scientific/Engineering
Classifier: Topic :: Multimedia :: Video
Requires-Python: >=3.8
License-File: LICENSE.txt
Requires-Dist: cupy-cuda12x
Dynamic: license-file
